tests/__init__.py
tests/test_zcwsearch.py
zcwsearch/__init__.py
zcwsearch/tools/__init__.py
zcwsearch/tools/utils.py
zcwsearch/tools/zcwsearch.py
zcwsearch/yamls/zcwsearch.yaml
zcwsearch-0.0.1.dist-info/METADATA
zcwsearch-0.0.1.dist-info/WHEEL
zcwsearch-0.0.1.dist-info/entry_points.txt
zcwsearch-0.0.1.dist-info/top_level.txt
zcwsearch-0.0.1.dist-info/RECORD
