Metadata-Version: 2.4
Name: zcwsearch
Version: 0.0.1
Summary: This is my tools package
Dynamic: summary
